[{"Year":2015,"Value":77,"GeoCode":null,"UNIT_MEASURE":"Number","SERIES":"Average of 13 International Health Regulations (IHR) core capacities [3.d.1]"},{"Year":2018,"Value":82,"GeoCode":null,"UNIT_MEASURE":"Number","SERIES":"Average of 13 International Health Regulations (IHR) core capacities [3.d.1]"},{"Year":2019,"Value":85,"GeoCode":null,"UNIT_MEASURE":"Number","SERIES":"Average of 13 International Health Regulations (IHR) core capacities [3.d.1]"},{"Year":2020,"Value":90,"GeoCode":null,"UNIT_MEASURE":"Number","SERIES":"Average of 13 International Health Regulations (IHR) core capacities [3.d.1]"},{"Year":2022,"Value":95,"GeoCode":null,"UNIT_MEASURE":"Number","SERIES":"Average of 13 International Health Regulations (IHR) core capacities [3.d.1]"}]